upload_to_sharepoint/__init__.py
upload_to_sharepoint/sharepoint_upload.py
upload_to_sharepoint-0.1.1.dist-info/METADATA
upload_to_sharepoint-0.1.1.dist-info/WHEEL
upload_to_sharepoint-0.1.1.dist-info/top_level.txt
upload_to_sharepoint-0.1.1.dist-info/RECORD
