Metadata-Version: 2.1
Name: upload-to-sharepoint
Version: 0.1.1
Summary: A library to upload files to SharePoint.
Home-page: https://your-repository-url-or-pypi-url
Author: Your Name
Author-email: your.email@example.com
Classifier: Programming Language :: Python :: 3
Classifier: License :: OSI Approved :: MIT License
Classifier: Operating System :: OS Independent
Requires-Python: >=3.6
Requires-Dist: office365-rest-python-client
Requires-Dist: keyring
